honeybee_energy_revive/__init__.py
honeybee_energy_revive/_extend_honeybee_energy_revive.py
honeybee_energy_revive/hvac/__init__.py
honeybee_energy_revive/hvac/equipment.py
honeybee_energy_revive/properties/__init__.py
honeybee_energy_revive/properties/ruleset.py
honeybee_energy_revive/properties/construction/__init__.py
honeybee_energy_revive/properties/construction/opaque.py
honeybee_energy_revive/properties/construction/shade.py
honeybee_energy_revive/properties/construction/window.py
honeybee_energy_revive/properties/construction/windowshade.py
honeybee_energy_revive/properties/generator/__init__.py
honeybee_energy_revive/properties/generator/pv.py
honeybee_energy_revive/properties/hot_water/__init__.py
honeybee_energy_revive/properties/hot_water/hw_program.py
honeybee_energy_revive/properties/hvac/__init__.py
honeybee_energy_revive/properties/hvac/allair.py
honeybee_energy_revive/properties/hvac/doas.py
honeybee_energy_revive/properties/hvac/heatcool.py
honeybee_energy_revive/properties/hvac/idealair.py
honeybee_energy_revive/properties/load/__init__.py
honeybee_energy_revive/properties/load/equipment.py
honeybee_energy_revive/properties/load/lighting.py
honeybee_energy_revive/properties/load/people.py
honeybee_energy_revive/properties/load/process.py
honeybee_energy_revive/properties/materials/__init__.py
honeybee_energy_revive/properties/materials/frame.py
honeybee_energy_revive/properties/materials/gas.py
honeybee_energy_revive/properties/materials/glazing.py
honeybee_energy_revive/properties/materials/opaque.py
honeybee_energy_revive/properties/materials/shade.py
honeybee_revive/CO2_measures.py
honeybee_revive/__init__.py
honeybee_revive/__main__.py
honeybee_revive/_extend_honeybee_revive.py
honeybee_revive/fuels.py
honeybee_revive/grid_region.py
honeybee_revive/national_emissions.py
honeybee_revive/cli/__init__.py
honeybee_revive/cli/graph.py
honeybee_revive/output/__init__.py
honeybee_revive/output/resilience_hourly_data.py
honeybee_revive-0.0.19.dist-info/licenses/LICENSE
honeybee_revive-0.0.19.dist-info/METADATA
honeybee_revive-0.0.19.dist-info/WHEEL
honeybee_revive-0.0.19.dist-info/top_level.txt
honeybee_revive-0.0.19.dist-info/RECORD
