Metadata-Version: 2.4
Name: honeybee-REVIVE
Version: 0.0.19
Summary: A Honeybee Extension for Phius REVIVE Modeling.
Author-email: Ed May <phtools@bldgtyp.com>
Maintainer-email: Ed May <phtools@bldgtyp.com>
License: GNU
Project-URL: homepage, https://www.passivehousetools.com/
Project-URL: repository, https://github.com/PH-Tools/honeybee_REVIVE/tree/main
Keywords: Honeybee,Honeybee-Energy,Passive House,Building Retrofit,Architecture,Energy Modeling,PHIUS,ADORB,Carbon Emissions,Embodied Carbon,Embodied CO2
Classifier: Programming Language :: Python :: 3
Classifier: License :: OSI Approved :: GNU General Public License v3 (GPLv3)
Classifier: Operating System :: OS Independent
Requires-Python: >=3.10
License-File: LICENSE
Requires-Dist: honeybee-energy>=1.116.17
Requires-Dist: pandas>=2.2.3
Requires-Dist: ph-units>=1.5.25
Requires-Dist: plotly>=5.24.1
Requires-Dist: pydantic<=1.10.18
Requires-Dist: rich>=13.8.1
Provides-Extra: dev
Requires-Dist: black; extra == "dev"
Requires-Dist: isort; extra == "dev"
Requires-Dist: pytest; extra == "dev"
Requires-Dist: coverage; extra == "dev"
Requires-Dist: Grasshopper-stubs; extra == "dev"
Requires-Dist: Rhino-stubs; extra == "dev"
Dynamic: license-file
